[
{"type":"header","version":"5.2.1","comment":"Export to JSON plugin for PHPMyAdmin"},
{"type":"database","name":"tugas_akhir"},
{"type":"table","name":"prodi","database":"tugas_akhir","data":
[
{"id_prodi":"1","nama_prodi":"D3 TEKNIK ELEKTRO"},
{"id_prodi":"2","nama_prodi":"D3 PERANCANGAN MEKANIK"},
{"id_prodi":"3","nama_prodi":"D3 PERAWATAN DAN PERBAIKAN  MESIN"},
{"id_prodi":"4","nama_prodi":"D4 TEKNIK MESIN DAN MANUFAKTUR"},
{"id_prodi":"5","nama_prodi":"D4 TEKNOLOGI REKAYASA PERANCANGAN MANUFAKTUR"},
{"id_prodi":"6","nama_prodi":"D4 TEKNIK ELEKTRONIKA"},
{"id_prodi":"7","nama_prodi":"D4 TEKNOLOGI REKAYASA PERANGKAT LUNAK"},
{"id_prodi":"8","nama_prodi":"D4 BISNIS DIGITAL"},
{"id_prodi":"9","nama_prodi":"D4 PERTANIAN PRESISI"}
]
}
]
